{"rfs":"2013","cables":[{"id":"southeast-asia-japan-cable-sjc","name":"Southeast Asia Japan Cable (SJC)","cable_id":1604},{"id":"taiwan-strait-express-1-tse-1","name":"Taiwan Strait Express-1 (TSE-1)","cable_id":1636},{"id":"silphium","name":"Silphium","cable_id":1665},{"id":"tonga-cable","name":"Tonga Cable","cable_id":1687},{"id":"guam-okinawa-kyushu-incheon-goki","name":"Guam Okinawa Kyushu Incheon (GOKI)","cable_id":1692},{"id":"omranepeg-cable-system","name":"OMRAN/EPEG Cable System","cable_id":1695},{"id":"st-thomas-st-croix-system","name":"St. Thomas-St. Croix System","cable_id":1756},{"id":"boracay-palawan-submarine-cable-system","name":"Boracay-Palawan Submarine Cable System","cable_id":1781},{"id":"saba-statia-cable-system-sscs","name":"Saba, Statia Cable System (SSCS)","cable_id":1807},{"id":"java-bali-cable-system-jbcs","name":"Java Bali Cable System (JBCS)","cable_id":1955},{"id":"lazaro-cardenas-manzanillo-santiago-submarine-cable-system-lcmsscs","name":"Lazaro Cardenas-Manzanillo Santiago Submarine Cable System (LCMSSCS)","cable_id":2032}],"landing_points":[{"id":"chikura-japan","landing_point_id":5885},{"id":"shantou-china","landing_point_id":5803},{"id":"nasugbu-philippines","landing_point_id":9603},{"id":"tuas-singapore","landing_point_id":5938},{"id":"chung-hom-kok-china","landing_point_id":5856},{"id":"telisai-brunei","landing_point_id":10309},{"id":"tanshui-taiwan","landing_point_id":5982},{"id":"fuzhou-china","landing_point_id":8620},{"id":"derna-libya","landing_point_id":7873},{"id":"chania-greece","landing_point_id":5723},{"id":"nukualofa-tonga","landing_point_id":9087},{"id":"suva-fiji","landing_point_id":4268},{"id":"okinawa-japan","landing_point_id":5886},{"id":"tumon-bay-gu-united-states","landing_point_id":5972},{"id":"kita-kyushu-japan","landing_point_id":5895},{"id":"diba-oman","landing_point_id":10579},{"id":"jask-iran","landing_point_id":6031},{"id":"khasab-oman","landing_point_id":7645},{"id":"chabahar-iran","landing_point_id":8849},{"id":"barka-oman","landing_point_id":8947},{"id":"vila-olga-virgin-islands-u-s-","landing_point_id":13402},{"id":"banana-bay-virgin-islands-u-s-","landing_point_id":13401},{"id":"flamingo-bay-virgin-islands-u-s-","landing_point_id":13400},{"id":"great-bay-virgin-islands-u-s-","landing_point_id":13399},{"id":"brewers-bay-virgin-islands-u-s-","landing_point_id":13398},{"id":"frederiksted-virgin-islands-u-s-","landing_point_id":13397},{"id":"christiansted-vi-united-states","landing_point_id":13396},{"id":"taytay-philippines","landing_point_id":14655},{"id":"san-jose-philippines","landing_point_id":7841},{"id":"coron-philippines","landing_point_id":9385},{"id":"great-bay-beach-saint-martin","landing_point_id":16123},{"id":"basseterre-saint-kitts-and-nevis","landing_point_id":4356},{"id":"gustavia-saint-barthlemy","landing_point_id":15452},{"id":"great-level-bay-bonaire-sint-eustatius-and-saba","landing_point_id":17404},{"id":"gallows-bay-bonaire-sint-eustatius-and-saba","landing_point_id":17405},{"id":"candi-kusuma-indonesia","landing_point_id":17173},{"id":"muncar-indonesia","landing_point_id":17172},{"id":"ixtapa-mexico","landing_point_id":17707},{"id":"ciudad-lzaro-crdenas-mexico","landing_point_id":14720},{"id":"manzanillo-mexico","landing_point_id":3843}]}
