{"name":"Israel","cables":[{"id":"lev-submarine-system","name":"Lev Submarine System","cable_id":1065},{"id":"mednautilus-submarine-system","name":"MedNautilus Submarine System","cable_id":1185},{"id":"tamares-north","name":"Tamares North","cable_id":1713},{"id":"jonah","name":"Jonah","cable_id":1677}],"landing_points":[{"id":"tel-aviv-israel","name":"Tel Aviv, Israel","landing_point_id":3213},{"id":"haifa-israel","name":"Haifa, Israel","landing_point_id":3905},{"id":"yeroskipos-cyprus","name":"Yeroskipos, Cyprus","landing_point_id":5811},{"id":"mazara-del-vallo-italy","name":"Mazara del Vallo, Italy","landing_point_id":3215},{"id":"catania-italy","name":"Catania, Italy","landing_point_id":3214},{"id":"istanbul-turkey","name":"Istanbul, Turkey","landing_point_id":3221},{"id":"chania-greece","name":"Chania, Greece","landing_point_id":5723},{"id":"athens-greece","name":"Athens, Greece","landing_point_id":3211},{"id":"pentaskhinos-cyprus","name":"Pentaskhinos, Cyprus","landing_point_id":5812},{"id":"bari-italy","name":"Bari, Italy","landing_point_id":3160}],"latlon":[{"latlon":"32.044599,34.769668"},{"latlon":"32.811420,34.998769"}]}
