{"name":"Marshall Islands","cables":[{"id":"hantru1-cable-system","name":"HANTRU1 Cable System","cable_id":1605}],"landing_points":[{"id":"majuro-marshall-islands","name":"Majuro, Marshall Islands","landing_point_id":9060},{"id":"kwajalein-marshall-islands","name":"Kwajalein, Marshall Islands","landing_point_id":7879},{"id":"piti-gu-united-states","name":"Piti, GU, United States","landing_point_id":5973},{"id":"pohnpei-micronesia","name":"Pohnpei, Micronesia","landing_point_id":9062}],"latlon":[{"latlon":"7.116242,171.185691"},{"latlon":"9.189776,167.424365"}]}
